
{"grow": ["usd", "ppc", "btc"],
 "lower": "0.0112494977903",
 "stats": {"bch_btc": "0.1514",
           "bch_dsh": "2.871",
           "bch_ltc": "9.245",
           "bch_rur": "85610.883",
           "bch_usd": "1409.903",
           "btc_eur": "7660.52456",
           "btc_rur": "565800",
           "btc_usd": "9317.718",
           "dsh_btc": "0.05241",
           "dsh_eth": "0.718",
           "dsh_eur": "402.349",
           "dsh_ltc": "3.21",
           "dsh_rur": "29584.312",
           "dsh_usd": "488.101",
           "eth_btc": "0.07293",
           "eth_ltc": "4.46",
           "eth_rur": "41210.31758",
           "eth_usd": "682.1",
           "eur_rur": "73.14697",
           "eur_usd": "1.20912",
           "ltc_btc": "0.01629",
           "ltc_eur": "125.339",
           "ltc_rur": "9216.6673",
           "ltc_usd": "151.705101",
           "nvc_btc": "0.00045",
           "nvc_usd": "4.196",
           "ppc_btc": "0.00027",
           "ppc_usd": "2.489",
           "usd_rur": "60.66",
           "zec_btc": "0.0316",
           "zec_usd": "295.463"},
 "upper": "-99.9927505022"}
